cci/__init__.py
cci-5.1.0.dist-info/LICENSE
cci-5.1.0.dist-info/METADATA
cci-5.1.0.dist-info/WHEEL
cci-5.1.0.dist-info/entry_points.txt
cci-5.1.0.dist-info/top_level.txt
cci-5.1.0.dist-info/RECORD
