Metadata-Version: 2.1
Name: cci
Version: 5.1.0
Summary: Use the Clang + LLVM toolchain as an interpreter for C code.
Author-email: Ellen Marie Dash <me@duckie.co>
License: MIT
Project-URL: repository, https://github.com/duckinator/cci
Classifier: Programming Language :: Python :: 3
Classifier: Programming Language :: Python :: 3.8
Classifier: Programming Language :: Python :: 3.9
Classifier: Programming Language :: Python :: 3.10
Classifier: Programming Language :: Python :: 3.11
Classifier: License :: OSI Approved :: MIT License
Classifier: Operating System :: OS Independent
Requires-Python: >=3.8
License-File: LICENSE
